pyacmi/__init__.py
pyacmi/acmi.py
pyacmi-1.2.4.dist-info/LICENSE
pyacmi-1.2.4.dist-info/METADATA
pyacmi-1.2.4.dist-info/WHEEL
pyacmi-1.2.4.dist-info/top_level.txt
pyacmi-1.2.4.dist-info/RECORD
