Metadata-Version: 2.1
Name: pyacmi
Version: 1.2.4
Summary: ACMI flight record file parser
Home-page: https://github.com/wangtong2015/pyacmi
Author: Wang Tong
Author-email: astroboythu@gmail.com
License: MIT
Keywords: acmi tacview
Classifier: Development Status :: 3 - Alpha
Classifier: Topic :: Games/Entertainment :: Simulation
Classifier: Intended Audience :: Developers
Classifier: Intended Audience :: End Users/Desktop
Classifier: License :: OSI Approved :: GNU Lesser General Public License v3 (LGPLv3)
Classifier: Programming Language :: Python :: 3.4
Classifier: Programming Language :: Python :: 3 :: Only
License-File: LICENSE
Requires-Dist: sortedcontainers
Requires-Dist: tqdm
